processdigit/__init__.py
processdigit/app.py
processdigit/process_image.py
processdigit-0.1.0.dist-info/DESCRIPTION.rst
processdigit-0.1.0.dist-info/METADATA
processdigit-0.1.0.dist-info/RECORD
processdigit-0.1.0.dist-info/WHEEL
processdigit-0.1.0.dist-info/metadata.json
processdigit-0.1.0.dist-info/top_level.txt
